pz_rail_base-1.2.8.dist-info/licenses/LICENSE
rail/cli/rail/__init__.py
rail/cli/rail/__main__.py
rail/cli/rail/commands.py
rail/cli/rail/options.py
rail/cli/rail/scripts.py
rail/core/__init__.py
rail/core/_version.py
rail/core/common_params.py
rail/core/data.py
rail/core/enums.py
rail/core/introspection.py
rail/core/model.py
rail/core/point_estimation.py
rail/core/stage.py
rail/core/utils.py
rail/creation/degrader.py
rail/creation/engine.py
rail/creation/noisifier.py
rail/creation/selector.py
rail/creation/degraders/addRandom.py
rail/creation/degraders/quantityCut.py
rail/estimation/classifier.py
rail/estimation/estimator.py
rail/estimation/informer.py
rail/estimation/summarizer.py
rail/estimation/algos/equal_count.py
rail/estimation/algos/gaussian_pz.py
rail/estimation/algos/naive_stack.py
rail/estimation/algos/point_est_hist.py
rail/estimation/algos/random_gauss.py
rail/estimation/algos/train_z.py
rail/estimation/algos/true_nz.py
rail/estimation/algos/uniform_binning.py
rail/estimation/algos/var_inf.py
rail/evaluation/dist_to_dist_evaluator.py
rail/evaluation/dist_to_point_evaluator.py
rail/evaluation/evaluator.py
rail/evaluation/point_to_point_evaluator.py
rail/evaluation/single_evaluator.py
rail/evaluation/stats_groups.py
rail/evaluation/metrics/base.py
rail/evaluation/metrics/cdeloss.py
rail/evaluation/metrics/pointestimates.py
rail/evaluation/metrics/tomography.py
rail/examples_data/.gitignore
rail/examples_data/creation_data/configs/flowModeler.yaml
rail/examples_data/creation_data/data/HSC_grid_settings.pkl
rail/examples_data/creation_data/data/README.md
rail/examples_data/creation_data/data/success_rate_data/DEEP2_success.txt
rail/examples_data/creation_data/data/success_rate_data/VVDSf02_I_success.txt
rail/examples_data/creation_data/data/success_rate_data/VVDSf02_z_bright_success.txt
rail/examples_data/creation_data/data/success_rate_data/VVDSf02_z_deep_success.txt
rail/examples_data/creation_data/data/success_rate_data/hsc_success.txt
pz_rail_base-1.2.8.dist-info/METADATA
pz_rail_base-1.2.8.dist-info/WHEEL
pz_rail_base-1.2.8.dist-info/entry_points.txt
pz_rail_base-1.2.8.dist-info/top_level.txt
pz_rail_base-1.2.8.dist-info/RECORD
