Metadata-Version: 2.4
Name: pz-rail-base
Version: 1.2.8
Author-email: "LSST Dark Energy Science Collaboration (DESC)" <later@later.com>
License: MIT License
Classifier: Development Status :: 4 - Beta
Classifier: License :: OSI Approved :: MIT License
Classifier: Intended Audience :: Developers
Classifier: Intended Audience :: Science/Research
Classifier: Operating System :: OS Independent
Classifier: Programming Language :: Python
Requires-Python: >=3.10
License-File: LICENSE
Requires-Dist: deprecated
Requires-Dist: pyyaml
Requires-Dist: numpy
Requires-Dist: click
Requires-Dist: ceci>=2.1
Requires-Dist: qp-prob>=1.0.0
Requires-Dist: scipy>=1.9.0
Provides-Extra: dev
Requires-Dist: qp-prob[full]; extra == "dev"
Requires-Dist: pytest; extra == "dev"
Requires-Dist: pytest-cov; extra == "dev"
Requires-Dist: pre-commit; extra == "dev"
Requires-Dist: pylint; extra == "dev"
Requires-Dist: jupyter; extra == "dev"
Dynamic: license-file
